turcy/__init__.py
turcy/pattern.py
turcy/pattern_builder.py
turcy/patterns_large.jsonl
turcy/patterns_small.jsonl
turcy/tree_dep_pattern.py
turcy/turcy.py
turcy/utils.py
turcy-0.0.42.data/data/patterns_large.jsonl
turcy-0.0.42.data/data/patterns_small.jsonl
turcy-0.0.42.dist-info/LICENSE
turcy-0.0.42.dist-info/METADATA
turcy-0.0.42.dist-info/WHEEL
turcy-0.0.42.dist-info/top_level.txt
turcy-0.0.42.dist-info/RECORD
