Metadata-Version: 2.1
Name: turcy
Version: 0.0.42
Summary: A package for German Open Informtion Extraction
Home-page: https://github.com/ChrisChross/turCy
Author: Christian Klose
Author-email: chris.klose@gmx.net
Keywords: openie turcy information extraction spacy
Classifier: Programming Language :: Python :: 3
Classifier: License :: OSI Approved :: MIT License
Classifier: Operating System :: OS Independent
Requires-Python: >=3.6
License-File: LICENSE
Requires-Dist: numpy (>=1.19.4)
Requires-Dist: pandas (==1.2.0)
Requires-Dist: spacy (>=3.0.1)
